dpixels/__init__.py
dpixels/canvas.py
dpixels/client.py
dpixels/color.py
dpixels/exceptions.py
dpixels/ratelimits.py
dpixels/source.py
dpixels-0.3.1.dist-info/LICENSE
dpixels-0.3.1.dist-info/METADATA
dpixels-0.3.1.dist-info/WHEEL
dpixels-0.3.1.dist-info/top_level.txt
dpixels-0.3.1.dist-info/RECORD
