Metadata-Version: 2.1
Name: dpixels
Version: 0.3.1
Summary: A(nother) wrapper for the Python Discord Pixels API.
Home-page: https://github.com/CircuitSacul/dpixels
Author: Circuit
License: MIT
Platform: UNKNOWN
Requires-Python: >=3.7
Requires-Dist: Pillow
Requires-Dist: aiohttp
